cbrctl
