Metadata-Version: 2.1
Name: cbrctl
Version: 0.0.1b6
Summary: Universal Command Line Environment for Carbonara.
Home-page: http://trycarbonara.com
Author: Carbonara Inc.
License: Apache License 2.0
Platform: UNKNOWN
Requires-Python: >= 3.7
